krsite_dl/__init__.py
krsite_dl/__main__.py
krsite_dl/extractor_registry.py
krsite_dl/krsite_dl.py
krsite_dl/__pyinstaller/__init__.py
krsite_dl/__pyinstaller/hook-krsite_dl.py
krsite_dl/downloader/__init__.py
krsite_dl/downloader/directory.py
krsite_dl/downloader/download.py
krsite_dl/extractor/__init__.py
krsite_dl/extractor/cosmopolitan.py
krsite_dl/extractor/dazedkorea.py
krsite_dl/extractor/dispatch.py
krsite_dl/extractor/elle.py
krsite_dl/extractor/esquirekorea.py
krsite_dl/extractor/genie.py
krsite_dl/extractor/harpersbazaar.py
krsite_dl/extractor/ilgansports.py
krsite_dl/extractor/imbcnews.py
krsite_dl/extractor/kodyssey.py
krsite_dl/extractor/lofficielkorea.py
krsite_dl/extractor/lofficielsingapore.py
krsite_dl/extractor/marieclairekorea.py
krsite_dl/extractor/mbc.py
krsite_dl/extractor/melon.py
krsite_dl/extractor/mikantimes.py
krsite_dl/extractor/nataliemu.py
krsite_dl/extractor/naverblog.py
krsite_dl/extractor/naverenter.py
krsite_dl/extractor/navernews.py
krsite_dl/extractor/naverpost.py
krsite_dl/extractor/news1.py
krsite_dl/extractor/newsen.py
krsite_dl/extractor/newsjamm.py
krsite_dl/extractor/nonno.py
krsite_dl/extractor/osen.py
krsite_dl/extractor/sbs.py
krsite_dl/extractor/sbskpop.py
krsite_dl/extractor/sbsnews.py
krsite_dl/extractor/sportsw.py
krsite_dl/extractor/spurjp.py
krsite_dl/extractor/tistory.py
krsite_dl/extractor/topstarnews.py
krsite_dl/extractor/tvjtbc.py
krsite_dl/extractor/tvreport.py
krsite_dl/extractor/vivi.py
krsite_dl/extractor/vogue.py
krsite_dl/extractor/wkorea.py
krsite_dl/utils/__init__.py
krsite_dl/utils/core.py
krsite_dl/utils/data_structure.py
krsite_dl/utils/essential.py
krsite_dl/utils/logger.py
krsite_dl/utils/misc.py
krsite_dl/utils/parser.py
krsite_dl/utils/url_selector.py
krsite_dl/utils/user_agent.py
krsite_dl-3.0.0.dist-info/METADATA
krsite_dl-3.0.0.dist-info/WHEEL
krsite_dl-3.0.0.dist-info/entry_points.txt
krsite_dl-3.0.0.dist-info/licenses/LICENSE
krsite_dl-3.0.0.dist-info/RECORD
