Metadata-Version: 2.4
Name: krsite-dl
Version: 3.0.0
Project-URL: Repository, https://github.com/krsite-dl/krsite-dl.git
License:                     GNU GENERAL PUBLIC LICENSE
License-File: LICENSE
Keywords: image,korean,site,video
Classifier: License :: OSI Approved :: GNU General Public License v3 (GPLv3)
Classifier: Programming Language :: Python :: 3
Classifier: Programming Language :: Python :: 3.7
Classifier: Programming Language :: Python :: 3.8
Classifier: Programming Language :: Python :: 3.9
Classifier: Programming Language :: Python :: 3.10
Classifier: Programming Language :: Python :: 3.11
Classifier: Programming Language :: Python :: 3.12
Classifier: Topic :: Internet :: WWW/HTTP
Classifier: Topic :: Multimedia :: Graphics
Classifier: Topic :: Multimedia :: Video
Classifier: Topic :: Software Development :: Libraries :: Python Modules
Classifier: Topic :: Utilities
Requires-Python: >=3.7
Requires-Dist: bs4>=0.0.2
Requires-Dist: importlib-metadata>=7.0.0
Requires-Dist: inquirer>=3.2.4
Requires-Dist: pydantic>=2.6.4
Requires-Dist: pytz>=2023.1
Requires-Dist: requests>=2.31.0
Requires-Dist: rich>=13.7.1
Requires-Dist: typing-extensions>=4.10.0
